dbnodeinidicator/__init__.py
dbnodeinidicator/core.py
dbnodeindicator-0.1.1.dist-info/METADATA
dbnodeindicator-0.1.1.dist-info/WHEEL
dbnodeindicator-0.1.1.dist-info/entry_points.txt
dbnodeindicator-0.1.1.dist-info/top_level.txt
dbnodeindicator-0.1.1.dist-info/RECORD
